RecordsKeeperPythonLib/__init__.py
RecordsKeeperPythonLib/address.py
RecordsKeeperPythonLib/assets.py
RecordsKeeperPythonLib/block.py
RecordsKeeperPythonLib/blockchain.py
RecordsKeeperPythonLib/permissions.py
RecordsKeeperPythonLib/stream.py
RecordsKeeperPythonLib/transaction.py
RecordsKeeperPythonLib/wallet.py
RecordsKeeperPythonLib/test/__init__.py
RecordsKeeperPythonLib/test/test_address.py
RecordsKeeperPythonLib/test/test_assets.py
RecordsKeeperPythonLib/test/test_block.py
RecordsKeeperPythonLib/test/test_blockchain.py
RecordsKeeperPythonLib/test/test_permissions.py
RecordsKeeperPythonLib/test/test_stream.py
RecordsKeeperPythonLib/test/test_transaction.py
RecordsKeeperPythonLib/test/test_wallet.py
RecordsKeeperPythonLib-0.2.2.dist-info/METADATA
RecordsKeeperPythonLib-0.2.2.dist-info/RECORD
RecordsKeeperPythonLib-0.2.2.dist-info/WHEEL
RecordsKeeperPythonLib-0.2.2.dist-info/top_level.txt
