Metadata-Version: 2.1
Name: RecordsKeeperPythonLib
Version: 0.2.2
Summary: RecordsKeeper Python library
Home-page: https://upload.pypi.org/legacy/
License: UNKNOWN
Keywords: recordskeeper,python,library
Platform: UNKNOWN
Classifier: Programming Language :: Python
Requires-Dist: requests
Requires-Dist: green
Requires-Dist: pyyaml
